LICENCE.txt
MANIFEST.in
README.rst
setup.py
automate_arduino/__init__.py
automate_arduino/arduino_actuators.py
automate_arduino/arduino_sensors.py
automate_arduino/arduino_service.py
automate_arduino.egg-info/PKG-INFO
automate_arduino.egg-info/SOURCES.txt
automate_arduino.egg-info/dependency_links.txt
automate_arduino.egg-info/entry_points.txt
automate_arduino.egg-info/requires.txt
automate_arduino.egg-info/top_level.txt