Metadata-Version: 1.1
Name: automate-arduino
Version: 0.9.2
Summary: Arduino Support for Automate
Home-page: http://github.com/tuomas2/automate-arduino
Author: Tuomas Airaksinen
Author-email: tuomas.airaksinen@gmail.com
License: GPL
Download-URL: https://pypi.python.org/pypi/automate-arduino
Keywords: automation,GPIO,Raspberry Pi,RPIO,traits
Platform: any
Classifier: Development Status :: 4 - Beta
Classifier: Environment :: Console
Classifier: Environment :: Web Environment
Classifier: Intended Audience :: Education
Classifier: Intended Audience :: End Users/Desktop
Classifier: Intended Audience :: Developers
Classifier: Intended Audience :: Information Technology
Classifier: License :: OSI Approved :: GNU General Public License (GPL)
Classifier: Operating System :: Microsoft :: Windows
Classifier: Operating System :: POSIX
Classifier: Operating System :: POSIX :: Linux
Classifier: Programming Language :: Python :: 2.7
Classifier: Topic :: Scientific/Engineering
Classifier: Topic :: Software Development
Classifier: Topic :: Software Development :: Libraries
